<?xpacket begin="﻿" id="W5M0MpCehiHzreSzNTczkc9d"?>
<x:xmpmeta xmlns:x="adobe:ns:meta/" x:xmptk="Adobe XMP Core 5.3-c011 66.145661, 2012/02/06-14:56:27        ">
   <rdf:RDF xmlns:rdf="http://www.w3.org/1999/02/22-rdf-syntax-ns#">
      <rdf:Description rdf:about=""
            xmlns:xmp="http://ns.adobe.com/xap/1.0/">
         <xmp:CreatorTool>Adobe Flash Professional CS5.5 - build 325</xmp:CreatorTool>
         <xmp:CreateDate>2011-11-10T15:58:59-02:00</xmp:CreateDate>
         <xmp:MetadataDate>2012-07-11T17:00:43-03:00</xmp:MetadataDate>
         <xmp:ModifyDate>2012-07-11T17:00:43-03:00</xmp:ModifyDate>
      </rdf:Description>
      <rdf:Description rdf:about=""
            xmlns:dc="http://purl.org/dc/elements/1.1/">
         <dc:format>application/vnd.adobe.fla</dc:format>
      </rdf:Description>
      <rdf:Description rdf:about=""
            xmlns:xmpMM="http://ns.adobe.com/xap/1.0/mm/"
            xmlns:stEvt="http://ns.adobe.com/xap/1.0/sType/ResourceEvent#"
            xmlns:stRef="http://ns.adobe.com/xap/1.0/sType/ResourceRef#">
         <xmpMM:InstanceID>xmp.iid:A07E1E1993CBE111A3DFF8392D407C99</xmpMM:InstanceID>
         <xmpMM:DocumentID>xmp.did:76FEB218C20BE111AD1BC6A4BEA01289</xmpMM:DocumentID>
         <xmpMM:OriginalDocumentID>xmp.did:75FEB218C20BE111AD1BC6A4BEA01289</xmpMM:OriginalDocumentID>
         <xmpMM:History>
            <rdf:Seq>
               <rdf:li rdf:parseType="Resource">
                  <stEvt:action>created</stEvt:action>
                  <stEvt:instanceID>xmp.iid:75FEB218C20BE111AD1BC6A4BEA01289</stEvt:instanceID>
                  <stEvt:when>2011-11-10T15:58:59-02:00</stEvt:when>
                  <stEvt:softwareAgent>Adobe Flash Professional CS5.5 - build 325</stEvt:softwareAgent>
               </rdf:li>
               <rdf:li rdf:parseType="Resource">
                  <stEvt:action>saved</stEvt:action>
                  <stEvt:instanceID>xmp.iid:76FEB218C20BE111AD1BC6A4BEA01289</stEvt:instanceID>
                  <stEvt:when>2011-11-10T16:24:02-02:00</stEvt:when>
                  <stEvt:softwareAgent>Adobe Flash Professional CS5.5 - build 325</stEvt:softwareAgent>
                  <stEvt:changed>/</stEvt:changed>
               </rdf:li>
               <rdf:li rdf:parseType="Resource">
                  <stEvt:action>created</stEvt:action>
                  <stEvt:instanceID>xmp.iid:B0DB75AC600CE111B580FD00EB7A4098</stEvt:instanceID>
                  <stEvt:when>2011-11-10T15:58:59-02:00</stEvt:when>
                  <stEvt:softwareAgent>Adobe Flash Professional CS5.5 - build 325</stEvt:softwareAgent>
               </rdf:li>
               <rdf:li rdf:parseType="Resource">
                  <stEvt:action>created</stEvt:action>
                  <stEvt:instanceID>xmp.iid:64E31853BB0EE111A2C79AFFFB92C950</stEvt:instanceID>
                  <stEvt:when>2011-11-10T15:58:59-02:00</stEvt:when>
                  <stEvt:softwareAgent>Adobe Flash Professional CS5.5 - build 325</stEvt:softwareAgent>
               </rdf:li>
               <rdf:li rdf:parseType="Resource">
                  <stEvt:action>created</stEvt:action>
                  <stEvt:instanceID>xmp.iid:B5D52CF0E00EE1119B00A5D6AE736FB1</stEvt:instanceID>
                  <stEvt:when>2011-11-10T15:58:59-02:00</stEvt:when>
                  <stEvt:softwareAgent>Adobe Flash Professional CS5.5 - build 325</stEvt:softwareAgent>
               </rdf:li>
               <rdf:li rdf:parseType="Resource">
                  <stEvt:action>created</stEvt:action>
                  <stEvt:instanceID>xmp.iid:DDC527485410E111A9AA9DB6B82F1FA5</stEvt:instanceID>
                  <stEvt:when>2011-11-10T15:58:59-02:00</stEvt:when>
                  <stEvt:softwareAgent>Adobe Flash Professional CS5.5 - build 325</stEvt:softwareAgent>
               </rdf:li>
               <rdf:li rdf:parseType="Resource">
                  <stEvt:action>created</stEvt:action>
                  <stEvt:instanceID>xmp.iid:5ADEB4171911E1118554FAFDA5F06636</stEvt:instanceID>
                  <stEvt:when>2011-11-10T15:58:59-02:00</stEvt:when>
                  <stEvt:softwareAgent>Adobe Flash Professional CS5.5 - build 325</stEvt:softwareAgent>
               </rdf:li>
               <rdf:li rdf:parseType="Resource">
                  <stEvt:action>created</stEvt:action>
                  <stEvt:instanceID>xmp.iid:986C827B4B23E111BCCF86486B0F6031</stEvt:instanceID>
                  <stEvt:when>2011-11-10T15:58:59-02:00</stEvt:when>
                  <stEvt:softwareAgent>Adobe Flash Professional CS5.5 - build 325</stEvt:softwareAgent>
               </rdf:li>
               <rdf:li rdf:parseType="Resource">
                  <stEvt:action>created</stEvt:action>
                  <stEvt:instanceID>xmp.iid:DF048D3C0725E111BD71A3A8557478DC</stEvt:instanceID>
                  <stEvt:when>2011-11-10T15:58:59-02:00</stEvt:when>
                  <stEvt:softwareAgent>Adobe Flash Professional CS5.5 - build 325</stEvt:softwareAgent>
               </rdf:li>
               <rdf:li rdf:parseType="Resource">
                  <stEvt:action>created</stEvt:action>
                  <stEvt:instanceID>xmp.iid:8C80CE42E725E111ABAFB69FFF94795D</stEvt:instanceID>
                  <stEvt:when>2011-11-10T15:58:59-02:00</stEvt:when>
                  <stEvt:softwareAgent>Adobe Flash Professional CS5.5 - build 325</stEvt:softwareAgent>
               </rdf:li>
               <rdf:li rdf:parseType="Resource">
                  <stEvt:action>created</stEvt:action>
                  <stEvt:instanceID>xmp.iid:E3BBC3054D26E11185FD9507AF43EFA1</stEvt:instanceID>
                  <stEvt:when>2011-11-10T15:58:59-02:00</stEvt:when>
                  <stEvt:softwareAgent>Adobe Flash Professional CS5.5 - build 325</stEvt:softwareAgent>
               </rdf:li>
               <rdf:li rdf:parseType="Resource">
                  <stEvt:action>created</stEvt:action>
                  <stEvt:instanceID>xmp.iid:9B69EE808E29E1119DD0C5E06DD631FB</stEvt:instanceID>
                  <stEvt:when>2011-11-10T15:58:59-02:00</stEvt:when>
                  <stEvt:softwareAgent>Adobe Flash Professional CS5.5 - build 325</stEvt:softwareAgent>
               </rdf:li>
               <rdf:li rdf:parseType="Resource">
                  <stEvt:action>created</stEvt:action>
                  <stEvt:instanceID>xmp.iid:CEA2BDD4BA2FE1118D57E3965B72A600</stEvt:instanceID>
                  <stEvt:when>2011-11-10T15:58:59-02:00</stEvt:when>
                  <stEvt:softwareAgent>Adobe Flash Professional CS5.5 - build 325</stEvt:softwareAgent>
               </rdf:li>
               <rdf:li rdf:parseType="Resource">
                  <stEvt:action>created</stEvt:action>
                  <stEvt:instanceID>xmp.iid:C6B699472B33E111BA48B44B367FA213</stEvt:instanceID>
                  <stEvt:when>2011-11-10T15:58:59-02:00</stEvt:when>
                  <stEvt:softwareAgent>Adobe Flash Professional CS5.5 - build 325</stEvt:softwareAgent>
               </rdf:li>
               <rdf:li rdf:parseType="Resource">
                  <stEvt:action>created</stEvt:action>
                  <stEvt:instanceID>xmp.iid:7C1B64F4EC33E11192218301E5491BD6</stEvt:instanceID>
                  <stEvt:when>2011-11-10T15:58:59-02:00</stEvt:when>
                  <stEvt:softwareAgent>Adobe Flash Professional CS5.5 - build 325</stEvt:softwareAgent>
               </rdf:li>
               <rdf:li rdf:parseType="Resource">
                  <stEvt:action>created</stEvt:action>
                  <stEvt:instanceID>xmp.iid:06EFB5CEB63EE111A526A2DCCEF579E5</stEvt:instanceID>
                  <stEvt:when>2011-11-10T15:58:59-02:00</stEvt:when>
                  <stEvt:softwareAgent>Adobe Flash Professional CS5.5 - build 325</stEvt:softwareAgent>
               </rdf:li>
               <rdf:li rdf:parseType="Resource">
                  <stEvt:action>created</stEvt:action>
                  <stEvt:instanceID>xmp.iid:CC6C4DBC2F45E1118F4EBCC6757AFCC6</stEvt:instanceID>
                  <stEvt:when>2011-11-10T15:58:59-02:00</stEvt:when>
                  <stEvt:softwareAgent>Adobe Flash Professional CS5.5 - build 325</stEvt:softwareAgent>
               </rdf:li>
               <rdf:li rdf:parseType="Resource">
                  <stEvt:action>created</stEvt:action>
                  <stEvt:instanceID>xmp.iid:AB81113D2546E111BB5DD85EAFAB91CA</stEvt:instanceID>
                  <stEvt:when>2011-11-10T15:58:59-02:00</stEvt:when>
                  <stEvt:softwareAgent>Adobe Flash Professional CS5.5 - build 325</stEvt:softwareAgent>
               </rdf:li>
               <rdf:li rdf:parseType="Resource">
                  <stEvt:action>created</stEvt:action>
                  <stEvt:instanceID>xmp.iid:9916AA48A647E111B870D874B8ECCD14</stEvt:instanceID>
                  <stEvt:when>2011-11-10T15:58:59-02:00</stEvt:when>
                  <stEvt:softwareAgent>Adobe Flash Professional CS5.5 - build 325</stEvt:softwareAgent>
               </rdf:li>
               <rdf:li rdf:parseType="Resource">
                  <stEvt:action>created</stEvt:action>
                  <stEvt:instanceID>xmp.iid:26935854324DE1118D70B79DFFB5B5A8</stEvt:instanceID>
                  <stEvt:when>2011-11-10T15:58:59-02:00</stEvt:when>
                  <stEvt:softwareAgent>Adobe Flash Professional CS5.5 - build 325</stEvt:softwareAgent>
               </rdf:li>
               <rdf:li rdf:parseType="Resource">
                  <stEvt:action>created</stEvt:action>
                  <stEvt:instanceID>xmp.iid:74AF27B93D5AE111AB54B16A9A80079E</stEvt:instanceID>
                  <stEvt:when>2011-11-10T15:58:59-02:00</stEvt:when>
                  <stEvt:softwareAgent>Adobe Flash Professional CS5.5 - build 325</stEvt:softwareAgent>
               </rdf:li>
               <rdf:li rdf:parseType="Resource">
                  <stEvt:action>created</stEvt:action>
                  <stEvt:instanceID>xmp.iid:A4C0ED1CE75BE111AFF285E9693DB1B9</stEvt:instanceID>
                  <stEvt:when>2011-11-10T15:58:59-02:00</stEvt:when>
                  <stEvt:softwareAgent>Adobe Flash Professional CS5.5 - build 325</stEvt:softwareAgent>
               </rdf:li>
               <rdf:li rdf:parseType="Resource">
                  <stEvt:action>created</stEvt:action>
                  <stEvt:instanceID>xmp.iid:C6AE631AE65FE111BA91A142A7B54ECB</stEvt:instanceID>
                  <stEvt:when>2011-11-10T15:58:59-02:00</stEvt:when>
                  <stEvt:softwareAgent>Adobe Flash Professional CS5.5 - build 325</stEvt:softwareAgent>
               </rdf:li>
               <rdf:li rdf:parseType="Resource">
                  <stEvt:action>created</stEvt:action>
                  <stEvt:instanceID>xmp.iid:CBAE631AE65FE111BA91A142A7B54ECB</stEvt:instanceID>
                  <stEvt:when>2011-11-10T15:58:59-02:00</stEvt:when>
                  <stEvt:softwareAgent>Adobe Flash Professional CS5.5 - build 325</stEvt:softwareAgent>
               </rdf:li>
               <rdf:li rdf:parseType="Resource">
                  <stEvt:action>created</stEvt:action>
                  <stEvt:instanceID>xmp.iid:50B39AF52B63E111BF4FE523628F70B3</stEvt:instanceID>
                  <stEvt:when>2011-11-10T15:58:59-02:00</stEvt:when>
                  <stEvt:softwareAgent>Adobe Flash Professional CS5.5 - build 325</stEvt:softwareAgent>
               </rdf:li>
               <rdf:li rdf:parseType="Resource">
                  <stEvt:action>created</stEvt:action>
                  <stEvt:instanceID>xmp.iid:B386D237A676E1118608D6645D35384A</stEvt:instanceID>
                  <stEvt:when>2011-11-10T15:58:59-02:00</stEvt:when>
                  <stEvt:softwareAgent>Adobe Flash Professional CS5.5 - build 325</stEvt:softwareAgent>
               </rdf:li>
               <rdf:li rdf:parseType="Resource">
                  <stEvt:action>created</stEvt:action>
                  <stEvt:instanceID>xmp.iid:34EF19DD56C5E111B3E2CF8FC44AD231</stEvt:instanceID>
                  <stEvt:when>2011-11-10T15:58:59-02:00</stEvt:when>
                  <stEvt:softwareAgent>Adobe Flash Professional CS6 - build 481</stEvt:softwareAgent>
               </rdf:li>
               <rdf:li rdf:parseType="Resource">
                  <stEvt:action>created</stEvt:action>
                  <stEvt:instanceID>xmp.iid:A07E1E1993CBE111A3DFF8392D407C99</stEvt:instanceID>
                  <stEvt:when>2011-11-10T15:58:59-02:00</stEvt:when>
                  <stEvt:softwareAgent>Adobe Flash Professional CS6 - build 481</stEvt:softwareAgent>
               </rdf:li>
            </rdf:Seq>
         </xmpMM:History>
         <xmpMM:DerivedFrom rdf:parseType="Resource">
            <stRef:instanceID>xmp.iid:75FEB218C20BE111AD1BC6A4BEA01289</stRef:instanceID>
            <stRef:documentID>xmp.did:75FEB218C20BE111AD1BC6A4BEA01289</stRef:documentID>
            <stRef:originalDocumentID>xmp.did:75FEB218C20BE111AD1BC6A4BEA01289</stRef:originalDocumentID>
         </xmpMM:DerivedFrom>
      </rdf:Description>
   </rdf:RDF>
</x:xmpmeta>
                                                                                                    
                                                                                                    
                                                                                                    
                                                                                                    
                                                                                                    
                                                                                                    
                                                                                                    
                                                                                                    
                                                                                                    
                                                                                                    
                                                                                                    
                                                                                                    
                                                                                                    
                                                                                                    
                                                                                                    
                                                                                                    
                                                                                                    
                                                                                                    
                                                                                                    
                                                                                                    
                           
<?xpacket end="w"?>